[
    {
        "numero de chassi": 123,
        "ano": "teste",
        "modelo": "teste",
        "marca": "teste",
        "lista de problemas_id": [
            123
        ]
    },
    {
        "numero de chassi": 125,
        "ano": "teste",
        "modelo": "teste",
        "marca": "teste",
        "lista de problemas_id": [
            123
        ]
    },
    {
        "numero de chassi": "4589-63",
        "ano": "2009",
        "modelo": "uno",
        "marca": "fiat",
        "lista de problemas_id": []
    },
    {
        "numero de chassi": "4589-63",
        "ano": "2009",
        "modelo": "uno",
        "marca": "fiat",
        "lista de problemas_id": []
    },
    {
        "numero de chassi": "7895",
        "ano": "2017",
        "modelo": "mobi",
        "marca": "fiat",
        "lista de problemas_id": []
    },
    {
        "numero de chassi": "7895",
        "ano": "2017",
        "modelo": "mobi",
        "marca": "fiat",
        "lista de problemas_id": []
    },
    {
        "numero de chassi": "4589-63",
        "ano": "2009",
        "modelo": "uno",
        "marca": "fiat",
        "lista de problemas_id": []
    },
    {
        "numero de chassi": "7895",
        "ano": "2017",
        "modelo": "mobi",
        "marca": "fiat",
        "lista de problemas_id": []
    }
]